chatroutes/__init__.py
chatroutes/client.py
chatroutes/exceptions.py
chatroutes/http_client.py
chatroutes/resources/__init__.py
chatroutes/resources/autobranch.py
chatroutes/resources/branches.py
chatroutes/resources/checkpoints.py
chatroutes/resources/conversations.py
chatroutes/resources/messages.py
chatroutes/types/__init__.py
chatroutes/types/autobranch.py
chatroutes/types/checkpoint.py
chatroutes/types/conversation.py
chatroutes-0.2.6.dist-info/licenses/LICENSE
chatroutes-0.2.6.dist-info/METADATA
chatroutes-0.2.6.dist-info/WHEEL
chatroutes-0.2.6.dist-info/top_level.txt
chatroutes-0.2.6.dist-info/RECORD
