Metadata-Version: 2.4
Name: chatroutes
Version: 0.2.6
Summary: Official Python SDK for ChatRoutes API - Conversation branching, AutoBranch, and multi-model AI chat
Home-page: https://github.com/chatroutes/chatroutes-python-sdk
Author: ChatRoutes
Author-email: ChatRoutes <support@chatroutes.com>
License-Expression: MIT
Project-URL: Homepage, https://chatroutes.com
Project-URL: Documentation, https://docs.chatroutes.com
Project-URL: Repository, https://github.com/chatroutes/chatroutes-python-sdk
Project-URL: Bug Tracker, https://github.com/chatroutes/chatroutes-python-sdk/issues
Keywords: chatroutes,ai,chat,conversation,branching,autobranch,multi-model,gpt,claude,api,sdk
Classifier: Development Status :: 4 - Beta
Classifier: Intended Audience :: Developers
Classifier: Topic :: Software Development :: Libraries :: Python Modules
Classifier: Programming Language :: Python :: 3
Classifier: Programming Language :: Python :: 3.8
Classifier: Programming Language :: Python :: 3.9
Classifier: Programming Language :: Python :: 3.10
Classifier: Programming Language :: Python :: 3.11
Classifier: Programming Language :: Python :: 3.12
Requires-Python: >=3.8
License-File: LICENSE
Requires-Dist: requests>=2.31.0
Requires-Dist: typing-extensions>=4.0.0
Provides-Extra: dev
Requires-Dist: pytest>=7.0.0; extra == "dev"
Requires-Dist: pytest-cov>=4.0.0; extra == "dev"
Requires-Dist: black>=23.0.0; extra == "dev"
Requires-Dist: mypy>=1.0.0; extra == "dev"
Requires-Dist: flake8>=6.0.0; extra == "dev"
Dynamic: author
Dynamic: home-page
Dynamic: license-file
Dynamic: requires-python
